yampy/__init__.py
yampy/authenticator.py
yampy/client.py
yampy/constants.py
yampy/errors.py
yampy/models.py
yampy/yammer.py
yampy/apis/__init__.py
yampy/apis/groups.py
yampy/apis/messages.py
yampy/apis/relationships.py
yampy/apis/threads.py
yampy/apis/topics.py
yampy/apis/users.py
yampy/apis/utils.py
yampy2-2.8.0.dist-info/LICENSE.txt
yampy2-2.8.0.dist-info/METADATA
yampy2-2.8.0.dist-info/WHEEL
yampy2-2.8.0.dist-info/top_level.txt
yampy2-2.8.0.dist-info/RECORD
